playnano/__init__.py
playnano/_version.py
playnano/afm_stack.py
playnano/errors.py
playnano/analysis/__init__.py
playnano/analysis/base.py
playnano/analysis/export.py
playnano/analysis/pipeline.py
playnano/analysis/modules/__init__.py
playnano/analysis/modules/count_nonzero.py
playnano/analysis/modules/dbscan_clustering.py
playnano/analysis/modules/feature_detection.py
playnano/analysis/modules/k_means_clustering.py
playnano/analysis/modules/log_blob_detection.py
playnano/analysis/modules/particle_tracking.py
playnano/analysis/modules/x_means_clustering.py
playnano/analysis/utils/__init__.py
playnano/analysis/utils/common.py
playnano/analysis/utils/frames.py
playnano/analysis/utils/loader.py
playnano/analysis/utils/particles.py
playnano/cli/__init__.py
playnano/cli/actions.py
playnano/cli/entrypoint.py
playnano/cli/handlers.py
playnano/cli/utils.py
playnano/fonts/Steps-Mono/COPYRIGHT.txt
playnano/fonts/Steps-Mono/FONTLOG.md
playnano/fonts/Steps-Mono/LICENSE.txt
playnano/fonts/Steps-Mono/README.md
playnano/fonts/Steps-Mono/Steps-Mono-Thin.otf
playnano/fonts/Steps-Mono/Steps-Mono.otf
playnano/fonts/basic/FONTLOG.txt
playnano/fonts/basic/LICENSE.txt
playnano/fonts/basic/README.md
playnano/fonts/basic/basic_regular.ttf
playnano/gui/__init__.py
playnano/gui/main.py
playnano/gui/window.py
playnano/gui/styles/dark_bluegreen.qss
playnano/gui/widgets/__init__.py
playnano/gui/widgets/controls.py
playnano/gui/widgets/viewer.py
playnano/io/__init__.py
playnano/io/data_loaders.py
playnano/io/export_data.py
playnano/io/gif_export.py
playnano/io/loader.py
playnano/io/formats/__init__.py
playnano/io/formats/read_asd.py
playnano/io/formats/read_h5jpk.py
playnano/io/formats/read_jpk_folder.py
playnano/io/formats/read_spm_folder.py
playnano/processing/__init__.py
playnano/processing/core.py
playnano/processing/filters.py
playnano/processing/mask_generators.py
playnano/processing/masked_filters.py
playnano/processing/pipeline.py
playnano/processing/stack_edit.py
playnano-0.2.2.dist-info/METADATA
playnano-0.2.2.dist-info/WHEEL
playnano-0.2.2.dist-info/entry_points.txt
playnano-0.2.2.dist-info/licenses/COPYING
playnano-0.2.2.dist-info/RECORD
