Metadata-Version: 2.4
Name: playnano
Version: 0.2.2
Summary: Python toolkit for processing and visualising high-speed AFM (Atomic Force Microscopy) video data.
Project-URL: Homepage, https://github.com/derollins/playNano
Project-URL: Documentation, https://derollins.github.io/playNano
Project-URL: Issues, https://github.com/derollins/playNano/issues
Project-URL: Changelog, https://github.com/derollins/playNano/blob/main/CHANGELOG.md
Author-email: "D. E. Rollins" <d.e.rollins@leeds.ac.uk>
License: GPL-3.0-or-later
License-File: COPYING
Keywords: AFM,FAIR data,HS-AFM,SPM,atomic force microscopy,biomolecular imaging,biophysics,clustering,data analysis,feature detection,flattening filters,high-speed AFM,image processing,image segmentation,materials science,microscopy data,nanometrology,nanoscopy,nanotechnology,open science,particle tracking,reproducible research,scanning probe microscopy,scientific computing,scientific visualization,surface analysis,time-series analysis,video analysis,video processing
Classifier: Intended Audience :: Science/Research
Classifier: License :: OSI Approved :: GNU General Public License v3 or later (GPLv3+)
Classifier: Natural Language :: English
Classifier: Operating System :: OS Independent
Classifier: Programming Language :: Python
Classifier: Programming Language :: Python :: 3
Classifier: Programming Language :: Python :: 3.10
Classifier: Programming Language :: Python :: 3.11
Classifier: Programming Language :: Python :: 3.12
Requires-Python: <3.13,>=3.10
Requires-Dist: afmreader
Requires-Dist: h5py
Requires-Dist: matplotlib
Requires-Dist: numpy<2.0,>=1.23
Requires-Dist: pandas
Requires-Dist: pillow
Requires-Dist: pyside6>=6.5
Requires-Dist: python-dateutil>=2.8
Requires-Dist: pyyaml>=6.0
Requires-Dist: scikit-learn
Requires-Dist: scipy
Requires-Dist: tifffile
Provides-Extra: dev
Requires-Dist: black; extra == 'dev'
Requires-Dist: flake8; extra == 'dev'
Requires-Dist: isort; extra == 'dev'
Requires-Dist: jsonschema; extra == 'dev'
Requires-Dist: pre-commit; extra == 'dev'
Requires-Dist: pytest-cov; extra == 'dev'
Requires-Dist: pytest-qt; extra == 'dev'
Requires-Dist: pytest>=7.0; extra == 'dev'
Requires-Dist: ruff; extra == 'dev'
Provides-Extra: docs
Requires-Dist: furo; extra == 'docs'
Requires-Dist: myst-parser; extra == 'docs'
Requires-Dist: nbsphinx; extra == 'docs'
Requires-Dist: sphinx; extra == 'docs'
Requires-Dist: sphinx-autoapi; extra == 'docs'
Requires-Dist: sphinx-multiversion; extra == 'docs'
Requires-Dist: sphinx-rtd-theme; extra == 'docs'
Requires-Dist: sphinxcontrib-programoutput; extra == 'docs'
Provides-Extra: notebooks
Requires-Dist: jupyter; extra == 'notebooks'
